traffic_monitor/__init__.py
traffic_monitor/const.py
traffic_monitor/sniffer.py
traffic_monitor-0.0.5.dist-info/METADATA
traffic_monitor-0.0.5.dist-info/WHEEL
traffic_monitor-0.0.5.dist-info/licenses/LICENSE
traffic_monitor-0.0.5.dist-info/RECORD
