Metadata-Version: 2.1
Name: traffic_monitor
Version: 0.0.5
Summary: Small package for traffic monitoring.
Project-URL: Homepage, https://github.com/AlejoSev/traffic_monitor
Project-URL: Bug Tracker, https://github.com/AlejoSev/traffic_monitor/issues
Author-email: Alejo Severini Montanari <alejoseverini@mi.unc.edu.ar>
License-File: LICENSE
Classifier: License :: OSI Approved :: MIT License
Classifier: Operating System :: OS Independent
Classifier: Programming Language :: Python :: 3
Requires-Python: >=3.6.9
Requires-Dist: cython>=0.29.32
Requires-Dist: python-libpcap>=0.4.0
